altspell_soundspel/__init__.py
altspell_soundspel/translate.py
altspell_soundspel/data/soundspel-dict.csv
altspell_soundspel-0.3.0.dist-info/WHEEL
altspell_soundspel-0.3.0.dist-info/METADATA
altspell_soundspel-0.3.0.dist-info/RECORD
