Metadata-Version: 2.4
Name: altspell-soundspel
Version: 0.3.0
Summary: Soundspel plugin for Altspell.
Author-email: Nicholas Johnson <njohnson@posteo.net>
Requires-Python: >=3.8,<4
Classifier: Development Status :: 3 - Alpha
Classifier: Intended Audience :: Developers
Classifier: Programming Language :: Python
Classifier: License :: OSI Approved :: GNU General Public License v3 or later (GPLv3+)
Classifier: Operating System :: OS Independent
Requires-Dist: altspell-plugins==0.2.2
Requires-Dist: nlp_provider==0.1.0
